structobject/__init__.py
structobject/compatibility.py
structobject/structField.py
structobject/structObject.py
structobject-1.0.1.dist-info/DESCRIPTION.rst
structobject-1.0.1.dist-info/METADATA
structobject-1.0.1.dist-info/RECORD
structobject-1.0.1.dist-info/WHEEL
structobject-1.0.1.dist-info/metadata.json
structobject-1.0.1.dist-info/top_level.txt
