Metadata-Version: 2.0
Name: structobject
Version: 1.0.1
Summary: A pythonic semantic for describing binary data structures
Home-page: https://github.com/wrenoud/structobject
Author: Weston Renoud
Author-email: wrenoud@gmail.com
License: UNKNOWN
Download-URL: https://github.com/wrenoud/structobject/tarball/v1.0.1
Keywords: struct,binary,data structures
Platform: UNKNOWN
